{
	"weapons":[
		{
			"id": 1,
			"name": "Basic_Sword",
			"category": 0,
			"type": 1,
			"rarity": 0,
			"loot_rate": 100,
			"cost": 1,
			"damage": 5,
			"att_speed": 1,
			"on_damage_dealt": "ApplyFire",
			"on_damage_receive": "KillHim",
			"model": "IronSword"
		},
		{
			"id": 2,
			"name": "Basic_Bow",
			"category": 8,
			"type": 0,
			"rarity": 0,
			"loot_rate": 100,
			"cost": 1,
			"damage": 5,
			"att_speed": 2,
			"on_damage_dealt": "ApplyFire",
			"on_damage_receive": "KillHim",
			"model": "WoodenBow"
		},
		{
			"id": 3,
			"name": "Basic_Spear",
			"category": 2,
			"type": 1,
			"rarity": 0,
			"loot_rate": 100,
			"cost": 1,
			"damage": 5,
			"att_speed": 2,
			"on_damage_dealt": "ApplyFire",
			"on_damage_receive": "KillHim",
			"model": "IronSpear"
		},
		{
			"id": 4,
			"name": "Basic_Dagger",
			"category": 10,
			"type": 1,
			"rarity": 0,
			"loot_rate": 100,
			"cost": 1,
			"damage": 5,
			"att_speed": 2,
			"on_damage_dealt": "ApplyFire",
			"on_damage_receive": "KillHim",
			"model": "IronDagger"
		},
		{
			"id": 5,
			"name": "Basic_Staff",
			"category": 9,
			"type": 0,
			"rarity": 0,
			"loot_rate": 100,
			"cost": 1,
			"damage": 5,
			"att_speed": 1,
			"on_damage_dealt": "ApplyFire",
			"on_damage_receive": "KillHim",
			"model": "WoodenStaff"
		},
	]
}