{"id":23,"spellTag":"OffensiveBuff","TypeSpell":"UniqueActivation","startFrom":"Caster","nameSpell":"BuffForKill","initialCooldown":0.0,"cooldown":10.0,"cost":5.0,"castTime":0.0,"isOnCooldown":false,"nbUse":-1,"sprite":null,"spellComponentFirstActivation":{"nameSpellComponent":"BuffForKillCompo","damageType":"Magical","actions":{"START":[{"startFrom":"Caster","actionOnEffectType":"BUFF_ATTACK","effect":{"nameEffect":"BleedBuff","typeEffect":"Bleed","level":1,"durationInSeconds":1.0,"durationBuff":3.0,"ressourceCost":0.0,"directionExpul":"Out","originExpulsion":"Entity","positionSrcDamage":{"x":0.0,"y":0.0,"z":0.0},"launcher":null,"currentCoroutine":null},"spellComponent":null,"damageDeal":0,"percentageToTrigger":100,"conditionToTrigger":null},{"startFrom":"Caster","actionOnEffectType":"BUFF_ATTACK","effect":{"nameEffect":"PoisonBuff","typeEffect":"Poison","level":1,"durationInSeconds":1.0,"durationBuff":3.0,"ressourceCost":0.0,"directionExpul":"Out","originExpulsion":"Entity","positionSrcDamage":{"x":0.0,"y":0.0,"z":0.0},"launcher":null,"currentCoroutine":null},"spellComponent":null,"damageDeal":0,"percentageToTrigger":100,"conditionToTrigger":null},{"startFrom":"Caster","actionOnEffectType":"BUFF_ATTACK","effect":{"nameEffect":"BurnBuff","typeEffect":"Burn","level":1,"durationInSeconds":1.0,"durationBuff":3.0,"ressourceCost":0.0,"directionExpul":"Out","originExpulsion":"Entity","positionSrcDamage":{"x":0.0,"y":0.0,"z":0.0},"launcher":null,"currentCoroutine":null},"spellComponent":null,"damageDeal":0,"percentageToTrigger":100,"conditionToTrigger":null}]},"spellDuration":3.0,"spellInterval":1.0,"conditionReduceCharge":"None","spellCharges":0,"trajectory":{"followCategory":"FOLLOW_TARGET","spellPath":null,"speed":0.0,"endOfPathInstruction":"Stop","disapearAtTheEndOfTrajectory":false,"objectToFollow":null,"initialParent":null},"spellToInstantiate":{"geometry":"Square","scale":{"x":1.0,"y":1.0,"z":1.0},"offsetStartPosition":{"x":0.0,"y":0.0,"z":0.0},"offsetObjectToInstantiate":{"x":0.0,"y":0.0,"z":0.0},"pathGameObjectToInstantiate":"Spells/AssassinSword3","incrementAmplitudeByTime":{"x":0.0,"y":0.0,"z":0.0},"passingThroughEntity":true},"damageMultiplierOnDistance":0.0,"appliesPlayerOnHitEffect":false,"canStopProjectile":false,"stopSpellComponentAtDamageReceived":false,"TypeSpellComponent":"Classic","originSpell":null,"currentCoroutine":null,"caster":null,"targetAtCast":null,"startAtPosition":{"x":0.0,"y":0.0,"z":0.0},"pathCreator":null,"spellPrefabController":null},"passiveSpellComponent":null,"deactivatePassiveWhenActive":false,"holdingCost":0.0,"maximumTimeHolding":0.0,"timeHolding":0.0,"spellComponentAfterHolding":null,"spellComponents":null,"isHolding":false,"nbSpellActivation":0,"currentCooldown":0.0}